LICENSE
README.md
setup.py
bin/gantt
doc/by-nc-sa.png
doc/gantt.svg
font/Songti.ttc
netkiller/__init__.py
netkiller/gantt.py
netkiller_gantt.egg-info/PKG-INFO
netkiller_gantt.egg-info/SOURCES.txt
netkiller_gantt.egg-info/dependency_links.txt
netkiller_gantt.egg-info/requires.txt
netkiller_gantt.egg-info/top_level.txt