Metadata-Version: 2.1
Name: netkiller-gantt
Version: 0.0.5
Summary: Best Gantt chart in Python
Home-page: https://www.netkiller.cn
Author: Neo Chen
Author-email: netkiller@msn.com
License: CC 3.0
Classifier: Environment :: Console
Classifier: Programming Language :: Python :: 3
Classifier: Operating System :: OS Independent
License-File: LICENSE
